empyrial/__init__.py
empyrial/main.py
empyrial-2.1.4.dist-info/METADATA
empyrial-2.1.4.dist-info/WHEEL
empyrial-2.1.4.dist-info/entry_points.txt
empyrial-2.1.4.dist-info/top_level.txt
empyrial-2.1.4.dist-info/RECORD
