Metadata-Version: 2.1
Name: empyrial
Version: 2.1.4
Summary: An Open Source Portfolio Management Framework for Everyone 投资组合管理
Home-page: https://github.com/ssantoshp/Empyrial
Classifier: Programming Language :: Python :: 3
Classifier: License :: OSI Approved :: BSD License
Classifier: Intended Audience :: Developers
Requires-Python: >=3.0
Requires-Dist: numpy
Requires-Dist: matplotlib
Requires-Dist: datetime
Requires-Dist: empyrical
Requires-Dist: quantstats
Requires-Dist: yfinance
Requires-Dist: ipython
Requires-Dist: fpdf
Requires-Dist: pyportfolioopt
